{"packages": {"spark": {"version": "0.0.0", "source": "github.com/HUSKI3/Spark", "author": "HUSKI3", "depends": "none"}, "nano": {"version": "5.6", "source": "https://www.nano-editor.org/dist/v5/nano-5.6.tar.xz"}, "iptables": {"version": "1.8.7", "source": "ftp://ftp.netfilter.org/pub/iptables/iptables-1.8.7.tar.bz2"}, "sudo": {"version": "1.9.5p2", "source": "ftp://ftp.sudo.ws/pub/sudo/sudo-1.9.5p2.tar.gz"}, "cracklib": {"version": "2.9.7", "source": "https://github.com/cracklib/cracklib/releases/download/v2.9.7/cracklib-2.9.7.tar.bz2"}, "libpwquality": {"version": "1.4.4", "source": "https://github.com/libpwquality/libpwquality/releases/download/libpwquality-1.4.4/libpwquality-1.4.4.tar.bz2"}, "linux-pam": {"version": "1.5.1", "source": "https://github.com/linux-pam/linux-pam/releases/download/v1.5.1/Linux-PAM-1.5.1-docs.tar.xz"}, "shadow": {"version": "4.8.1", "source": "https://github.com/shadow-maint/shadow/releases/download/4.8.1/shadow-4.8.1.tar.xz"}, "vim": {"version": "8.2.2433", "source": "http://anduin.linuxfromscratch.org/BLFS/vim/vim-8.2.2433.tar.gz"}, "ICU": {"version": "69.1", "source": "https://github.com/unicode-org/icu/releases/download/release-69-1/icu4c-69_1-src.tgz"}}}